COPYING
MANIFEST.in
README.rst
bootstrap-buildout.py
buildout.cfg
setup.py
bob/__init__.py
bob.palmvein.egg-info/PKG-INFO
bob.palmvein.egg-info/SOURCES.txt
bob.palmvein.egg-info/dependency_links.txt
bob.palmvein.egg-info/entry_points.txt
bob.palmvein.egg-info/namespace_packages.txt
bob.palmvein.egg-info/not-zip-safe
bob.palmvein.egg-info/requires.txt
bob.palmvein.egg-info/top_level.txt
bob/palmvein/__init__.py
bob/palmvein/utils.py
bob/palmvein/configurations/__init__.py
bob/palmvein/configurations/tools.py
bob/palmvein/configurations/databases/__init__.py
bob/palmvein/configurations/databases/casiapalm.py
bob/palmvein/configurations/databases/verapalm.py
bob/palmvein/configurations/databases/verapalmTS.py
bob/palmvein/configurations/databases/verapalmraw.py
bob/palmvein/configurations/databases/verapalmroi.py
bob/palmvein/configurations/databases/verapalmroiTS.py
bob/palmvein/configurations/features/__init__.py
bob/palmvein/configurations/features/lbp.py
bob/palmvein/configurations/grid/__init__.py
bob/palmvein/configurations/grid/demanding.py
bob/palmvein/configurations/grid/gbu.py
bob/palmvein/configurations/grid/gpu.py
bob/palmvein/configurations/grid/gpu2.py
bob/palmvein/configurations/grid/gpu3.py
bob/palmvein/configurations/grid/grid.py
bob/palmvein/configurations/grid/large.py
bob/palmvein/configurations/grid/local.py
bob/palmvein/configurations/grid/small.py
bob/palmvein/configurations/grid/very_demanding.py
bob/palmvein/configurations/preprocessing/__init__.py
bob/palmvein/configurations/preprocessing/palm_crop.py
bob/palmvein/configurations/preprocessing/palm_crop_CGF.py
bob/palmvein/features/LocalBinaryPatterns.py
bob/palmvein/features/__init__.py
bob/palmvein/preprocessing/PalmCrop.py
bob/palmvein/preprocessing/__init__.py
bob/palmvein/script/__init__.py
bob/palmvein/script/evaluatesys.py
bob/palmvein/script/palmveinverify.py
bob/palmvein/script/scores2spoofingfile.py
bob/palmvein/script/scoresanalysis.py
bob/palmvein/tests/__init__.py
bob/palmvein/tests/test.py
bob/palmvein/tools/HammingDistance.py
bob/palmvein/tools/MiuraMatch.py
bob/palmvein/tools/__init__.py
doc/conf.py
doc/contribute.rst
doc/evaluate.rst
doc/experiments.rst
doc/index.rst
doc/installation.rst
doc/links.rst
doc/references.rst
doc/satellite.rst