Metadata-Version: 1.1
Name: bob.palmvein
Version: 2.0.0a1
Summary: Palmvein recognition based on Bob and the facereclib
Home-page: https://github.com/bioidiap/bob.palmvein
Author: Pedro Tome
Author-email: pedro.tome@idiap.ch
License: LICENSE.txt
Keywords: Palmvein recognition,palmvein verification,reproducible research,facereclib
Platform: UNKNOWN
Classifier: Framework :: Bob
Classifier: Development Status :: 4 - Beta
Classifier: Intended Audience :: Developers
Classifier: License :: OSI Approved :: GNU General Public License v3 (GPLv3)
Classifier: Natural Language :: English
Classifier: Programming Language :: Python
Classifier: Topic :: Scientific/Engineering :: Artificial Intelligence
Classifier: Topic :: Software Development :: Libraries :: Python Modules
